README.rst
setup.py
tempest_db/TempestDBService.py
tempest_db/__init__.py
tempest_db/constants.py
tempest_db/ttypes.py
tempest_db/twitter_2010_example.py
tempest_db.egg-info/PKG-INFO
tempest_db.egg-info/SOURCES.txt
tempest_db.egg-info/dependency_links.txt
tempest_db.egg-info/requires.txt
tempest_db.egg-info/top_level.txt