Metadata-Version: 1.1
Name: tempest-db
Version: 0.14.0
Summary: Python client for the Tempest Graph Database.
Home-page: https://github.com/teapot-co/tempest
Author: Peter Lofgren
Author-email: plofgren@cs.stanford.edu
License: Apache
Keywords: graph database network
Platform: UNKNOWN
Classifier: Development Status :: 4 - Beta
Classifier: License :: OSI Approved :: Apache Software License
Classifier: Programming Language :: Python :: 2
Classifier: Programming Language :: Python :: 2.6
Classifier: Programming Language :: Python :: 2.7
